{"code": "AKFYE", "updated": "2026-07-02 20:45", "quarters": [{"period": "2026/03", "satislar": 1761854000.0, "brut_kar": 383970000.0, "esas_faaliyet_kari": 0.0, "favok": null, "net_kar": 482481000.0, "brut_marj": 21.8, "favok_marj": null, "net_marj": 27.4, "donen_varliklar": 2393156000.0, "duran_varliklar": 0.0, "nakit_finansal_yatirim": 1435590000.0, "finansal_borclar_kv": 3074715000.0, "ozkaynaklar": 62456935000.0}, {"period": "2025/12", "satislar": 6377833527.0, "brut_kar": 1964791416.0, "esas_faaliyet_kari": 0.0, "favok": null, "net_kar": 2145531292.0, "brut_marj": 30.8, "favok_marj": null, "net_marj": 33.6, "donen_varliklar": 3326238091.0, "duran_varliklar": 0.0, "nakit_finansal_yatirim": 2338419603.0, "finansal_borclar_kv": 3267028777.0, "ozkaynaklar": 61452226962.0}, {"period": "2025/09", "satislar": 4421956000.0, "brut_kar": 1349149000.0, "esas_faaliyet_kari": 0.0, "favok": null, "net_kar": 959236000.0, "brut_marj": 30.5, "favok_marj": null, "net_marj": 21.7, "donen_varliklar": 4559121000.0, "duran_varliklar": 0.0, "nakit_finansal_yatirim": 3235754000.0, "finansal_borclar_kv": 2884711000.0, "ozkaynaklar": 47538984000.0}, {"period": "2025/06", "satislar": 2716751000.0, "brut_kar": 873811000.0, "esas_faaliyet_kari": 0.0, "favok": null, "net_kar": 744695000.0, "brut_marj": 32.2, "favok_marj": null, "net_marj": 27.4, "donen_varliklar": 4232566000.0, "duran_varliklar": 0.0, "nakit_finansal_yatirim": 1848718000.0, "finansal_borclar_kv": 2521561000.0, "ozkaynaklar": 43820582000.0}, {"period": "2025/03", "satislar": 1523789000.0, "brut_kar": 440769000.0, "esas_faaliyet_kari": 0.0, "favok": null, "net_kar": 835729000.0, "brut_marj": 28.9, "favok_marj": null, "net_marj": 54.8, "donen_varliklar": 3852517000.0, "duran_varliklar": 0.0, "nakit_finansal_yatirim": 2116907000.0, "finansal_borclar_kv": 2190031000.0, "ozkaynaklar": 41093977000.0}, {"period": "2024/12", "satislar": 6672075462.0, "brut_kar": 2609729942.0, "esas_faaliyet_kari": 0.0, "favok": null, "net_kar": 205966933.0, "brut_marj": 39.1, "favok_marj": null, "net_marj": 3.1, "donen_varliklar": 3204038708.0, "duran_varliklar": 0.0, "nakit_finansal_yatirim": 1516788159.0, "finansal_borclar_kv": 2126250330.0, "ozkaynaklar": 47538655307.0}, {"period": "2024/09", "satislar": 5076652000.0, "brut_kar": 2047143000.0, "esas_faaliyet_kari": 0.0, "favok": null, "net_kar": 690106000.0, "brut_marj": 40.3, "favok_marj": null, "net_marj": 13.6, "donen_varliklar": 4021152000.0, "duran_varliklar": 0.0, "nakit_finansal_yatirim": 2709927000.0, "finansal_borclar_kv": 2645543000.0, "ozkaynaklar": 30415339000.0}, {"period": "2024/06", "satislar": 3378810000.0, "brut_kar": 1584240000.0, "esas_faaliyet_kari": 0.0, "favok": null, "net_kar": 770312000.0, "brut_marj": 46.9, "favok_marj": null, "net_marj": 22.8, "donen_varliklar": 1675425000.0, "duran_varliklar": 0.0, "nakit_finansal_yatirim": 742593000.0, "finansal_borclar_kv": 2521792000.0, "ozkaynaklar": 27849314000.0}, {"period": "2024/03", "satislar": 1585425000.0, "brut_kar": 747456000.0, "esas_faaliyet_kari": 0.0, "favok": null, "net_kar": 1017022000.0, "brut_marj": 47.1, "favok_marj": null, "net_marj": 64.1, "donen_varliklar": 2244521000.0, "duran_varliklar": 0.0, "nakit_finansal_yatirim": 1617991000.0, "finansal_borclar_kv": 2671419000.0, "ozkaynaklar": 24626738000.0}, {"period": "2023/12", "satislar": 6299589000.0, "brut_kar": 3176691000.0, "esas_faaliyet_kari": 0.0, "favok": null, "net_kar": 6568281000.0, "brut_marj": 50.4, "favok_marj": null, "net_marj": 104.3, "donen_varliklar": 2461093000.0, "duran_varliklar": 0.0, "nakit_finansal_yatirim": 1647612000.0, "finansal_borclar_kv": 3467423000.0, "ozkaynaklar": 29500146000.0}]}