{"code": "ARZUM", "updated": "2026-07-03 02:15", "quarters": [{"period": "2026/03", "satislar": 1015467101.0, "brut_kar": 0.0, "esas_faaliyet_kari": -16726274.0, "favok": 20184905.0, "net_kar": -82587584.0, "brut_marj": 0.0, "favok_marj": 2.0, "net_marj": -8.1, "donen_varliklar": 1967033865.0, "duran_varliklar": null, "nakit_finansal_yatirim": 154537620.0, "finansal_borclar_kv": 1451342773.0, "ozkaynaklar": -421692226.0}, {"period": "2025/12", "satislar": 1476906239.0, "brut_kar": 0.0, "esas_faaliyet_kari": -462441679.0, "favok": -399607579.0, "net_kar": -546087627.0, "brut_marj": 0.0, "favok_marj": -27.1, "net_marj": -37.0, "donen_varliklar": 2042997737.0, "duran_varliklar": null, "nakit_finansal_yatirim": 185534545.0, "finansal_borclar_kv": 1409769714.0, "ozkaynaklar": -302303224.0}, {"period": "2025/09", "satislar": 1188132251.0, "brut_kar": 0.0, "esas_faaliyet_kari": -110313387.0, "favok": -61204681.0, "net_kar": -266101193.0, "brut_marj": 0.0, "favok_marj": -5.2, "net_marj": -22.4, "donen_varliklar": 2513312348.0, "duran_varliklar": null, "nakit_finansal_yatirim": 276086212.0, "finansal_borclar_kv": 1406338523.0, "ozkaynaklar": 155342101.0}, {"period": "2025/06", "satislar": 1186076859.0, "brut_kar": 0.0, "esas_faaliyet_kari": 73117370.0, "favok": 103809718.0, "net_kar": -112398743.0, "brut_marj": 0.0, "favok_marj": 8.8, "net_marj": -9.5, "donen_varliklar": 3632374848.0, "duran_varliklar": null, "nakit_finansal_yatirim": 582106230.0, "finansal_borclar_kv": 2372823641.0, "ozkaynaklar": 102688963.0}, {"period": "2025/03", "satislar": 1963708020.0, "brut_kar": 0.0, "esas_faaliyet_kari": 195021142.0, "favok": 247261487.0, "net_kar": -100072338.0, "brut_marj": 0.0, "favok_marj": 12.6, "net_marj": -5.1, "donen_varliklar": 3222071147.0, "duran_varliklar": null, "nakit_finansal_yatirim": 246799508.0, "finansal_borclar_kv": 2042853044.0, "ozkaynaklar": 221107445.0}, {"period": "2024/12", "satislar": 2173549006.0, "brut_kar": 0.0, "esas_faaliyet_kari": 113558339.0, "favok": 198580474.0, "net_kar": -114974522.0, "brut_marj": 0.0, "favok_marj": 9.1, "net_marj": -5.3, "donen_varliklar": 3695021575.0, "duran_varliklar": null, "nakit_finansal_yatirim": 194243996.0, "finansal_borclar_kv": 2307608804.0, "ozkaynaklar": 372028249.0}, {"period": "2024/09", "satislar": 1834394752.0, "brut_kar": 0.0, "esas_faaliyet_kari": 170673529.0, "favok": 192753277.0, "net_kar": -209899134.0, "brut_marj": 0.0, "favok_marj": 10.5, "net_marj": -11.4, "donen_varliklar": 2519441512.0, "duran_varliklar": null, "nakit_finansal_yatirim": 120294841.0, "finansal_borclar_kv": 1577967010.0, "ozkaynaklar": 333148076.0}, {"period": "2024/06", "satislar": 1834134538.0, "brut_kar": 0.0, "esas_faaliyet_kari": 160658436.0, "favok": 182453044.0, "net_kar": -123687529.0, "brut_marj": 0.0, "favok_marj": 9.9, "net_marj": -6.7, "donen_varliklar": 2567135758.0, "duran_varliklar": null, "nakit_finansal_yatirim": 258834465.0, "finansal_borclar_kv": 1435323819.0, "ozkaynaklar": 434884229.0}, {"period": "2024/03", "satislar": 1416677333.0, "brut_kar": 0.0, "esas_faaliyet_kari": 113735926.0, "favok": 144579783.0, "net_kar": -74961179.0, "brut_marj": 0.0, "favok_marj": 10.2, "net_marj": -5.3, "donen_varliklar": 2485513181.0, "duran_varliklar": null, "nakit_finansal_yatirim": 367205441.0, "finansal_borclar_kv": 1221934553.0, "ozkaynaklar": 485083103.0}, {"period": "2023/12", "satislar": 1780906655.0, "brut_kar": 0.0, "esas_faaliyet_kari": 173724490.0, "favok": 204257490.0, "net_kar": -1918508.0, "brut_marj": 0.0, "favok_marj": 11.5, "net_marj": -0.1, "donen_varliklar": 2723505996.0, "duran_varliklar": null, "nakit_finansal_yatirim": 342803195.0, "finansal_borclar_kv": 1309615878.0, "ozkaynaklar": 678085232.0}]}