{"code": "BANVT", "type": "sinai", "updated": "2026-07-12 10:33", "quarters": [{"period": "2026/03", "satislar": 7890170046.0, "brut_kar": -216640525.0, "esas_faaliyet_kari": -1143270238.0, "favok": -558914662.0, "net_kar": -796663172.0, "brut_marj": -2.7, "favok_marj": -7.1, "net_marj": -10.1, "roe": -37.6, "roic": -19.7, "donen_varliklar": 15584504770.0, "duran_varliklar": 9446557428.0, "nakit_finansal_yatirim": 6003713912.0, "finansal_borclar_kv": 4625286355.0, "net_borc": -1300641933.0, "net_borc_favok": 0.63, "ozkaynaklar": 11386108733.0}, {"period": "2025/12", "satislar": 12192544062.0, "brut_kar": -212730200.0, "esas_faaliyet_kari": -1591599463.0, "favok": -839073153.0, "net_kar": -2461290841.0, "brut_marj": -1.7, "favok_marj": -6.9, "net_marj": -20.2, "roe": -27.1, "roic": -12.5, "donen_varliklar": 18131064140.0, "duran_varliklar": 9582253919.0, "nakit_finansal_yatirim": 7720489097.0, "finansal_borclar_kv": 4893000821.0, "net_borc": -2728940786.0, "net_borc_favok": 3.68, "ozkaynaklar": 12182546524.0}, {"period": "2025/09", "satislar": 9197076238.0, "brut_kar": 267774171.0, "esas_faaliyet_kari": -676430132.0, "favok": -138175767.0, "net_kar": -689327378.0, "brut_marj": 2.9, "favok_marj": -1.5, "net_marj": -7.5, "roe": -6.9, "roic": -2.9, "donen_varliklar": 15745939957.0, "duran_varliklar": 7339120602.0, "nakit_finansal_yatirim": 6123256161.0, "finansal_borclar_kv": 3950881525.0, "net_borc": -2081137257.0, "net_borc_favok": -1.47, "ozkaynaklar": 11581454553.0}, {"period": "2025/06", "satislar": 5425988163.0, "brut_kar": -197108942.0, "esas_faaliyet_kari": -809680024.0, "favok": -533640506.0, "net_kar": -258836808.0, "brut_marj": -3.6, "favok_marj": -9.8, "net_marj": -4.8, "roe": 19.7, "roic": 10.0, "donen_varliklar": 15003472837.0, "duran_varliklar": 6904215522.0, "nakit_finansal_yatirim": 6388292415.0, "finansal_borclar_kv": 2792552722.0, "net_borc": -3498347309.0, "net_borc_favok": -0.87, "ozkaynaklar": 11394854022.0}, {"period": "2025/03", "satislar": 10039441359.0, "brut_kar": 1181725297.0, "esas_faaliyet_kari": 205200807.0, "favok": 769025162.0, "net_kar": -18528356.0, "brut_marj": 11.8, "favok_marj": 7.7, "net_marj": -0.2, "roe": 45.2, "roic": 27.6, "donen_varliklar": 14199296774.0, "duran_varliklar": 6611210931.0, "nakit_finansal_yatirim": 6392082527.0, "finansal_borclar_kv": 2199079813.0, "net_borc": -4060178308.0, "net_borc_favok": -0.57, "ozkaynaklar": 10996671268.0}, {"period": "2024/12", "satislar": 11214174224.0, "brut_kar": 2195968369.0, "esas_faaliyet_kari": 678302696.0, "favok": 1316406946.0, "net_kar": 255798181.0, "brut_marj": 19.6, "favok_marj": 11.7, "net_marj": 2.3, "roe": 48.4, "roic": 27.3, "donen_varliklar": 16554961885.0, "duran_varliklar": 8065242066.0, "nakit_finansal_yatirim": 6935773504.0, "finansal_borclar_kv": 2513042766.0, "net_borc": -4226803514.0, "net_borc_favok": -0.53, "ozkaynaklar": 13094647152.0}, {"period": "2024/09", "satislar": 11300452805.0, "brut_kar": 2760282276.0, "esas_faaliyet_kari": 1831881258.0, "favok": 2456474497.0, "net_kar": 1870299774.0, "brut_marj": 24.4, "favok_marj": 21.7, "net_marj": 16.6, "roe": 83.4, "roic": 38.6, "donen_varliklar": 11359552472.0, "duran_varliklar": 5883364006.0, "nakit_finansal_yatirim": 3550642143.0, "finansal_borclar_kv": 1614061545.0, "net_borc": -1748118800.0, "net_borc_favok": -0.22, "ozkaynaklar": 9146340750.0}, {"period": "2024/06", "satislar": 10044884267.0, "brut_kar": 2908713698.0, "esas_faaliyet_kari": 2180928423.0, "favok": 2629827166.0, "net_kar": 1664360595.0, "brut_marj": 29.0, "favok_marj": 26.2, "net_marj": 16.6, "roe": 79.5, "roic": 35.4, "donen_varliklar": 9709830492.0, "duran_varliklar": 5558851549.0, "nakit_finansal_yatirim": 3179774205.0, "finansal_borclar_kv": 1286902767.0, "net_borc": -1689500594.0, "net_borc_favok": -0.28, "ozkaynaklar": 7398485693.0}, {"period": "2024/03", "satislar": 8715788421.0, "brut_kar": 1808207498.0, "esas_faaliyet_kari": 1057217478.0, "favok": 1537876217.0, "net_kar": 920459149.0, "brut_marj": 20.7, "favok_marj": 17.6, "net_marj": 10.6, "roe": 61.9, "roic": 29.3, "donen_varliklar": 7678542708.0, "duran_varliklar": 5227327955.0, "nakit_finansal_yatirim": 1687194633.0, "finansal_borclar_kv": 1064156583.0, "net_borc": -389833279.0, "net_borc_favok": -0.08, "ozkaynaklar": 5703927032.0}, {"period": "2023/12", "satislar": 9166997939.0, "brut_kar": 1367343688.0, "esas_faaliyet_kari": 562771495.0, "favok": 1177047008.0, "net_kar": 464708932.0, "brut_marj": 14.9, "favok_marj": 12.8, "net_marj": 5.1, "roe": 26.5, "roic": 11.4, "donen_varliklar": 9321093884.0, "duran_varliklar": 6461266784.0, "nakit_finansal_yatirim": 1817196016.0, "finansal_borclar_kv": 1846666465.0, "net_borc": 145774111.0, "net_borc_favok": 0.05, "ozkaynaklar": 6354846066.0}]}