{"code": "DIRIT", "type": "sinai", "updated": "2026-07-05 11:31", "quarters": [{"period": "2026/03", "satislar": 3436491.0, "brut_kar": 1266.0, "esas_faaliyet_kari": -1366688.0, "favok": -1366688.0, "net_kar": -2418566.0, "brut_marj": 0.0, "favok_marj": -39.8, "net_marj": -70.4, "roe": -242.9, "roic": -32.4, "donen_varliklar": 32606890.0, "duran_varliklar": 3579.0, "nakit_finansal_yatirim": 27802.0, "finansal_borclar_kv": 0.0, "net_borc": -27802.0, "net_borc_favok": 0.0, "ozkaynaklar": 16511882.0}, {"period": "2025/12", "satislar": 383674.0, "brut_kar": 18577.0, "esas_faaliyet_kari": -1808832.0, "favok": -1808832.0, "net_kar": -171080002.0, "brut_marj": 4.8, "favok_marj": -471.5, "net_marj": -44589.9, "roe": -184.7, "roic": -25.2, "donen_varliklar": 38142370.0, "duran_varliklar": 169183.0, "nakit_finansal_yatirim": 30712.0, "finansal_borclar_kv": 0.0, "net_borc": -30712.0, "net_borc_favok": 0.0, "ozkaynaklar": 18931355.0}, {"period": "2025/09", "satislar": 0.0, "brut_kar": 0.0, "esas_faaliyet_kari": -1007407.0, "favok": -1007407.0, "net_kar": 2079405.0, "brut_marj": null, "favok_marj": null, "net_marj": null, "roe": -27.3, "roic": -2.8, "donen_varliklar": 30918896.0, "duran_varliklar": 139591953.0, "nakit_finansal_yatirim": 36771.0, "finansal_borclar_kv": 0.0, "net_borc": 2774471.0, "net_borc_favok": -0.47, "ozkaynaklar": 159408734.0}, {"period": "2025/06", "satislar": -1179581.0, "brut_kar": -57113.0, "esas_faaliyet_kari": -2948757.0, "favok": -2948757.0, "net_kar": -2958300.0, "brut_marj": 4.8, "favok_marj": 250.0, "net_marj": 250.8, "roe": -30.4, "roic": -4.4, "donen_varliklar": 31015481.0, "duran_varliklar": 111947729.0, "nakit_finansal_yatirim": 35771.0, "finansal_borclar_kv": 0.0, "net_borc": 2775471.0, "net_borc_favok": -0.45, "ozkaynaklar": 132047295.0}, {"period": "2025/03", "satislar": 5000969.0, "brut_kar": 242137.0, "esas_faaliyet_kari": -605202.0, "favok": -605202.0, "net_kar": -605202.0, "brut_marj": 4.8, "favok_marj": -12.1, "net_marj": -12.1, "roe": -34.1, "roic": -4.1, "donen_varliklar": 38929421.0, "duran_varliklar": 111816494.0, "nakit_finansal_yatirim": 35751.0, "finansal_borclar_kv": 11451412.0, "net_borc": 11524783.0, "net_borc_favok": -2.67, "ozkaynaklar": 127062583.0}, {"period": "2024/12", "satislar": -5463.0, "brut_kar": -5463.0, "esas_faaliyet_kari": -1451611.0, "favok": -1393362.0, "net_kar": -65409771.0, "brut_marj": 100.0, "favok_marj": 25505.4, "net_marj": 1197323.3, "roe": -31.3, "roic": -4.1, "donen_varliklar": 50048290.0, "duran_varliklar": 146322229.0, "nakit_finansal_yatirim": 51508.0, "finansal_borclar_kv": 14989020.0, "net_borc": 14937512.0, "net_borc_favok": -2.18, "ozkaynaklar": 167893848.0}, {"period": "2024/09", "satislar": 53153.0, "brut_kar": 53153.0, "esas_faaliyet_kari": -2848116.0, "favok": -1101813.0, "net_kar": 2161724.0, "brut_marj": 100.0, "favok_marj": -2072.9, "net_marj": 4067.0, "roe": 41.5, "roic": 3.0, "donen_varliklar": 46921806.0, "duran_varliklar": 312136150.0, "nakit_finansal_yatirim": 159488.0, "finansal_borclar_kv": 12111912.0, "net_borc": 11952424.0, "net_borc_favok": 0.71, "ozkaynaklar": 330108452.0}, {"period": "2024/06", "satislar": 58400.0, "brut_kar": 58400.0, "esas_faaliyet_kari": -2581966.0, "favok": -1095428.0, "net_kar": 1384032.0, "brut_marj": 100.0, "favok_marj": -1875.7, "net_marj": 2369.9, "roe": 44.4, "roic": 3.9, "donen_varliklar": 46896105.0, "duran_varliklar": 289126073.0, "nakit_finansal_yatirim": 159488.0, "finansal_borclar_kv": 12111912.0, "net_borc": 11952424.0, "net_borc_favok": 0.66, "ozkaynaklar": 306883614.0}, {"period": "2024/03", "satislar": 87500.0, "brut_kar": 87500.0, "esas_faaliyet_kari": -3134753.0, "favok": -3134753.0, "net_kar": -1443713.0, "brut_marj": 100.0, "favok_marj": -3582.6, "net_marj": -1650.0, "roe": 50.4, "roic": 6.2, "donen_varliklar": 45474646.0, "duran_varliklar": 218995203.0, "nakit_finansal_yatirim": 140179.0, "finansal_borclar_kv": 9300670.0, "net_borc": 9160491.0, "net_borc_favok": 0.45, "ozkaynaklar": 239005697.0}, {"period": "2023/12", "satislar": 27836752.0, "brut_kar": 22664039.0, "esas_faaliyet_kari": 22161765.0, "favok": 22161765.0, "net_kar": 76786611.0, "brut_marj": 81.4, "favok_marj": 79.6, "net_marj": 275.8, "roe": 41.5, "roic": 5.8, "donen_varliklar": 42265853.0, "duran_varliklar": 218995205.0, "nakit_finansal_yatirim": 159582.0, "finansal_borclar_kv": 12111912.0, "net_borc": 11952330.0, "net_borc_favok": 0.51, "ozkaynaklar": 236540971.0}]}