{"code": "DOGUB", "updated": "2026-07-03 02:24", "quarters": [{"period": "2026/03", "satislar": 9616739.0, "brut_kar": 0.0, "esas_faaliyet_kari": -7567713.0, "favok": -6796914.0, "net_kar": -7099673.0, "brut_marj": 0.0, "favok_marj": -70.7, "net_marj": -73.8, "donen_varliklar": 54132689.0, "duran_varliklar": null, "nakit_finansal_yatirim": 13903787.0, "finansal_borclar_kv": 0.0, "ozkaynaklar": 58292296.0}, {"period": "2025/12", "satislar": 27223802.0, "brut_kar": 0.0, "esas_faaliyet_kari": -7557954.0, "favok": -6454277.0, "net_kar": -19516685.0, "brut_marj": 0.0, "favok_marj": -23.7, "net_marj": -71.7, "donen_varliklar": 49588506.0, "duran_varliklar": null, "nakit_finansal_yatirim": 16812326.0, "finansal_borclar_kv": 0.0, "ozkaynaklar": 65708746.0}, {"period": "2025/09", "satislar": 20294221.0, "brut_kar": 0.0, "esas_faaliyet_kari": -11112753.0, "favok": -10360400.0, "net_kar": -12188206.0, "brut_marj": 0.0, "favok_marj": -51.1, "net_marj": -60.1, "donen_varliklar": 58359415.0, "duran_varliklar": null, "nakit_finansal_yatirim": 10692722.0, "finansal_borclar_kv": 0.0, "ozkaynaklar": 69931193.0}, {"period": "2025/06", "satislar": 11124330.0, "brut_kar": 0.0, "esas_faaliyet_kari": -2455277.0, "favok": -1975118.0, "net_kar": -14080885.0, "brut_marj": 0.0, "favok_marj": -17.8, "net_marj": -126.6, "donen_varliklar": 50693759.0, "duran_varliklar": null, "nakit_finansal_yatirim": 3128679.0, "finansal_borclar_kv": 0.0, "ozkaynaklar": 74827364.0}, {"period": "2025/03", "satislar": 15457976.0, "brut_kar": 0.0, "esas_faaliyet_kari": -9472323.0, "favok": -8713181.0, "net_kar": -9876537.0, "brut_marj": 0.0, "favok_marj": -56.4, "net_marj": -63.9, "donen_varliklar": 43120483.0, "duran_varliklar": null, "nakit_finansal_yatirim": 126384.0, "finansal_borclar_kv": 0.0, "ozkaynaklar": 85922329.0}, {"period": "2024/12", "satislar": 22014494.0, "brut_kar": 0.0, "esas_faaliyet_kari": -17689396.0, "favok": -17680479.0, "net_kar": -21329738.0, "brut_marj": 0.0, "favok_marj": -80.3, "net_marj": -96.9, "donen_varliklar": 50119585.0, "duran_varliklar": null, "nakit_finansal_yatirim": 2274466.0, "finansal_borclar_kv": 0.0, "ozkaynaklar": 111228999.0}, {"period": "2024/09", "satislar": 15496584.0, "brut_kar": 0.0, "esas_faaliyet_kari": -6834121.0, "favok": -5761959.0, "net_kar": -6685134.0, "brut_marj": 0.0, "favok_marj": -37.2, "net_marj": -43.1, "donen_varliklar": 42349920.0, "duran_varliklar": null, "nakit_finansal_yatirim": 440977.0, "finansal_borclar_kv": 0.0, "ozkaynaklar": 94572129.0}, {"period": "2024/06", "satislar": 11066115.0, "brut_kar": 0.0, "esas_faaliyet_kari": -3752109.0, "favok": -2824895.0, "net_kar": -7702394.0, "brut_marj": 0.0, "favok_marj": -25.5, "net_marj": -69.6, "donen_varliklar": 39827230.0, "duran_varliklar": null, "nakit_finansal_yatirim": 91474.0, "finansal_borclar_kv": 0.0, "ozkaynaklar": 90425375.0}, {"period": "2024/03", "satislar": 16597941.0, "brut_kar": 0.0, "esas_faaliyet_kari": -9962289.0, "favok": -9127512.0, "net_kar": -12240058.0, "brut_marj": 0.0, "favok_marj": -55.0, "net_marj": -73.7, "donen_varliklar": 44052354.0, "duran_varliklar": null, "nakit_finansal_yatirim": 209783.0, "finansal_borclar_kv": 0.0, "ozkaynaklar": 88567053.0}, {"period": "2023/12", "satislar": 27649362.0, "brut_kar": 0.0, "esas_faaliyet_kari": -2294012.0, "favok": -606455.0, "net_kar": -7579544.0, "brut_marj": 0.0, "favok_marj": -2.2, "net_marj": -27.4, "donen_varliklar": 48807778.0, "duran_varliklar": null, "nakit_finansal_yatirim": 2433325.0, "finansal_borclar_kv": 0.0, "ozkaynaklar": 122257327.0}]}