{"code": "EYGYO", "updated": "2026-07-02 20:59", "quarters": [{"period": "2026/03", "satislar": 43493255.0, "brut_kar": -749213.0, "esas_faaliyet_kari": 0.0, "favok": null, "net_kar": -73334422.0, "brut_marj": -1.7, "favok_marj": null, "net_marj": -168.6, "donen_varliklar": 814879905.0, "duran_varliklar": 0.0, "nakit_finansal_yatirim": 6144347.0, "finansal_borclar_kv": 433880066.0, "ozkaynaklar": 1936877995.0}, {"period": "2025/12", "satislar": 780752105.0, "brut_kar": 3760601.0, "esas_faaliyet_kari": 0.0, "favok": null, "net_kar": -722228319.0, "brut_marj": 0.5, "favok_marj": null, "net_marj": -92.5, "donen_varliklar": 927367060.0, "duran_varliklar": 0.0, "nakit_finansal_yatirim": 40730112.0, "finansal_borclar_kv": 488303555.0, "ozkaynaklar": 2009995720.0}, {"period": "2025/09", "satislar": 487744259.0, "brut_kar": -9887183.0, "esas_faaliyet_kari": 0.0, "favok": null, "net_kar": -277369683.0, "brut_marj": -2.0, "favok_marj": null, "net_marj": -56.9, "donen_varliklar": 938894183.0, "duran_varliklar": 0.0, "nakit_finansal_yatirim": 4205720.0, "finansal_borclar_kv": 391112773.0, "ozkaynaklar": 2120338754.0}, {"period": "2025/06", "satislar": 215274686.0, "brut_kar": -10549419.0, "esas_faaliyet_kari": 0.0, "favok": null, "net_kar": -146016254.0, "brut_marj": -4.9, "favok_marj": null, "net_marj": -67.8, "donen_varliklar": 1167525377.0, "duran_varliklar": 0.0, "nakit_finansal_yatirim": 12134270.0, "finansal_borclar_kv": 650917852.0, "ozkaynaklar": 2084490385.0}, {"period": "2025/03", "satislar": 116299637.0, "brut_kar": -12342905.0, "esas_faaliyet_kari": 0.0, "favok": null, "net_kar": -111894916.0, "brut_marj": -10.6, "favok_marj": null, "net_marj": -96.2, "donen_varliklar": 1216345634.0, "duran_varliklar": 0.0, "nakit_finansal_yatirim": 13793125.0, "finansal_borclar_kv": 519572988.0, "ozkaynaklar": 1991929630.0}, {"period": "2024/12", "satislar": 2250512770.0, "brut_kar": 1002141935.0, "esas_faaliyet_kari": 0.0, "favok": null, "net_kar": 157568175.0, "brut_marj": 44.5, "favok_marj": null, "net_marj": 7.0, "donen_varliklar": 1572836179.0, "duran_varliklar": 0.0, "nakit_finansal_yatirim": 15602558.0, "finansal_borclar_kv": 645752533.0, "ozkaynaklar": 2502371126.0}, {"period": "2024/09", "satislar": 264487041.0, "brut_kar": 21723807.0, "esas_faaliyet_kari": 0.0, "favok": null, "net_kar": 23524393.0, "brut_marj": 8.2, "favok_marj": null, "net_marj": 8.9, "donen_varliklar": 1833564791.0, "duran_varliklar": 0.0, "nakit_finansal_yatirim": 90084945.0, "finansal_borclar_kv": 453342554.0, "ozkaynaklar": 1767787695.0}, {"period": "2024/06", "satislar": 190062986.0, "brut_kar": 42433832.0, "esas_faaliyet_kari": 0.0, "favok": null, "net_kar": 8699255.0, "brut_marj": 22.3, "favok_marj": null, "net_marj": 4.6, "donen_varliklar": 1612482327.0, "duran_varliklar": 0.0, "nakit_finansal_yatirim": 26343338.0, "finansal_borclar_kv": 432038679.0, "ozkaynaklar": 1632333077.0}, {"period": "2024/03", "satislar": 114819658.0, "brut_kar": 81546039.0, "esas_faaliyet_kari": 0.0, "favok": null, "net_kar": 14384536.0, "brut_marj": 71.0, "favok_marj": null, "net_marj": 12.5, "donen_varliklar": 1531091218.0, "duran_varliklar": 0.0, "nakit_finansal_yatirim": 69111826.0, "finansal_borclar_kv": 507268238.0, "ozkaynaklar": 1511417545.0}, {"period": "2023/12", "satislar": 2021013787.0, "brut_kar": -252994679.0, "esas_faaliyet_kari": 0.0, "favok": null, "net_kar": 350118044.0, "brut_marj": -12.5, "favok_marj": null, "net_marj": 17.3, "donen_varliklar": 2095627245.0, "duran_varliklar": 0.0, "nakit_finansal_yatirim": 104664574.0, "finansal_borclar_kv": 642929608.0, "ozkaynaklar": 1879100003.0}]}