{"code": "GSDHO", "updated": "2026-07-03 02:31", "quarters": [{"period": "2026/03", "satislar": 475945000.0, "brut_kar": 0.0, "esas_faaliyet_kari": 467453000.0, "favok": 582899000.0, "net_kar": -420715000.0, "brut_marj": 0.0, "favok_marj": 122.5, "net_marj": -88.4, "donen_varliklar": 10187831000.0, "duran_varliklar": null, "nakit_finansal_yatirim": 6199061000.0, "finansal_borclar_kv": 624488000.0, "ozkaynaklar": 14019071000.0}, {"period": "2025/12", "satislar": 690032032.0, "brut_kar": 0.0, "esas_faaliyet_kari": 882282315.0, "favok": 1024725055.0, "net_kar": 573313728.0, "brut_marj": 0.0, "favok_marj": 148.5, "net_marj": 83.1, "donen_varliklar": 10980708134.0, "duran_varliklar": null, "nakit_finansal_yatirim": 7633707664.0, "finansal_borclar_kv": 671708296.0, "ozkaynaklar": 14684629391.0}, {"period": "2025/09", "satislar": 441328000.0, "brut_kar": 0.0, "esas_faaliyet_kari": 513739000.0, "favok": 659367000.0, "net_kar": 13921000.0, "brut_marj": 0.0, "favok_marj": 149.4, "net_marj": 3.2, "donen_varliklar": 8083980000.0, "duran_varliklar": null, "nakit_finansal_yatirim": 5542109000.0, "finansal_borclar_kv": 499255000.0, "ozkaynaklar": 12543522000.0}, {"period": "2025/06", "satislar": 279645000.0, "brut_kar": 0.0, "esas_faaliyet_kari": 246020000.0, "favok": 301385000.0, "net_kar": 18884000.0, "brut_marj": 0.0, "favok_marj": 107.8, "net_marj": 6.8, "donen_varliklar": 8851125000.0, "duran_varliklar": null, "nakit_finansal_yatirim": 4920997000.0, "finansal_borclar_kv": 384553000.0, "ozkaynaklar": 11665695000.0}, {"period": "2025/03", "satislar": 401789000.0, "brut_kar": 0.0, "esas_faaliyet_kari": 428765000.0, "favok": 552518000.0, "net_kar": -311550000.0, "brut_marj": 0.0, "favok_marj": 137.5, "net_marj": -77.5, "donen_varliklar": 8229758000.0, "duran_varliklar": null, "nakit_finansal_yatirim": 3949349000.0, "finansal_borclar_kv": 360821000.0, "ozkaynaklar": 11025771000.0}, {"period": "2024/12", "satislar": 448327322.0, "brut_kar": 0.0, "esas_faaliyet_kari": 483451890.0, "favok": 596405457.0, "net_kar": 424534550.0, "brut_marj": 0.0, "favok_marj": 133.0, "net_marj": 94.7, "donen_varliklar": 10664258767.0, "duran_varliklar": null, "nakit_finansal_yatirim": 6594113373.0, "finansal_borclar_kv": 507724799.0, "ozkaynaklar": 13393973780.0}, {"period": "2024/09", "satislar": 464759000.0, "brut_kar": 0.0, "esas_faaliyet_kari": 598534000.0, "favok": 736818000.0, "net_kar": 127799000.0, "brut_marj": 0.0, "favok_marj": 158.5, "net_marj": 27.5, "donen_varliklar": 6993668000.0, "duran_varliklar": null, "nakit_finansal_yatirim": 4613173000.0, "finansal_borclar_kv": 386688000.0, "ozkaynaklar": 9388589000.0}, {"period": "2024/06", "satislar": 462644000.0, "brut_kar": 0.0, "esas_faaliyet_kari": 452565000.0, "favok": 540408000.0, "net_kar": 416811000.0, "brut_marj": 0.0, "favok_marj": 116.8, "net_marj": 90.1, "donen_varliklar": 6374179000.0, "duran_varliklar": null, "nakit_finansal_yatirim": 3051484000.0, "finansal_borclar_kv": 243210000.0, "ozkaynaklar": 8625531000.0}, {"period": "2024/03", "satislar": 479120000.0, "brut_kar": 0.0, "esas_faaliyet_kari": 449320000.0, "favok": 538133000.0, "net_kar": -411627000.0, "brut_marj": 0.0, "favok_marj": 112.3, "net_marj": -85.9, "donen_varliklar": 5466318000.0, "duran_varliklar": null, "nakit_finansal_yatirim": 2332877000.0, "finansal_borclar_kv": 165970000.0, "ozkaynaklar": 7915566000.0}, {"period": "2023/12", "satislar": 369686000.0, "brut_kar": 0.0, "esas_faaliyet_kari": 307787000.0, "favok": 648012000.0, "net_kar": -1205594000.0, "brut_marj": 0.0, "favok_marj": 175.3, "net_marj": -326.1, "donen_varliklar": 6216357000.0, "duran_varliklar": null, "nakit_finansal_yatirim": 3671421000.0, "finansal_borclar_kv": 202065000.0, "ozkaynaklar": 10216151000.0}]}