{"code": "HUBVC", "type": "sinai", "updated": "2026-07-04 10:35", "quarters": [{"period": "2026/03", "satislar": 8653712.0, "brut_kar": 8653712.0, "esas_faaliyet_kari": 2105797.0, "favok": 2536286.0, "net_kar": 1475420.0, "brut_marj": 100.0, "favok_marj": 29.3, "net_marj": 17.0, "roe": -53.1, "roic": -6.8, "donen_varliklar": 36508124.0, "duran_varliklar": 578399806.0, "nakit_finansal_yatirim": 15742054.0, "finansal_borclar_kv": 863809.0, "net_borc": -13892309.0, "net_borc_favok": 0.27, "ozkaynaklar": 580181807.0}, {"period": "2025/12", "satislar": -34305986.0, "brut_kar": -33474083.0, "esas_faaliyet_kari": -44205065.0, "favok": -43169101.0, "net_kar": 17612807.0, "brut_marj": 97.6, "favok_marj": 125.8, "net_marj": -51.3, "roe": -41.7, "roic": -8.1, "donen_varliklar": 34949739.0, "duran_varliklar": 581581560.0, "nakit_finansal_yatirim": 13768274.0, "finansal_borclar_kv": 966333.0, "net_borc": -11628994.0, "net_borc_favok": 0.19, "ozkaynaklar": 578695684.0}, {"period": "2025/09", "satislar": 246395.0, "brut_kar": 140019.0, "esas_faaliyet_kari": -6372327.0, "favok": -6157942.0, "net_kar": 71466843.0, "brut_marj": 56.8, "favok_marj": -2499.2, "net_marj": 29005.0, "roe": -73.0, "roic": 4.0, "donen_varliklar": 20341447.0, "duran_varliklar": 735642957.0, "nakit_finansal_yatirim": 235467.0, "finansal_borclar_kv": 0.0, "net_borc": -235467.0, "net_borc_favok": -0.01, "ozkaynaklar": 728904584.0}, {"period": "2025/06", "satislar": -677455.0, "brut_kar": -1402982.0, "esas_faaliyet_kari": -4674031.0, "favok": -4487153.0, "net_kar": -401930930.0, "brut_marj": 207.1, "favok_marj": 662.4, "net_marj": 59329.5, "roe": -84.5, "roic": 4.5, "donen_varliklar": 604143117.0, "duran_varliklar": 2683953.0, "nakit_finansal_yatirim": 585070848.0, "finansal_borclar_kv": 0.0, "net_borc": -585070848.0, "net_borc_favok": -15.99, "ozkaynaklar": 585420883.0}, {"period": "2025/03", "satislar": 2656809.0, "brut_kar": 2656809.0, "esas_faaliyet_kari": -7515022.0, "favok": -7102154.0, "net_kar": 28835878.0, "brut_marj": 100.0, "favok_marj": -267.3, "net_marj": 1085.4, "roe": -26.4, "roic": 4.2, "donen_varliklar": 19289773.0, "duran_varliklar": 589948633.0, "nakit_finansal_yatirim": 1554216.0, "finansal_borclar_kv": 0.0, "net_borc": -1554216.0, "net_borc_favok": -0.04, "ozkaynaklar": 593060506.0}, {"period": "2024/12", "satislar": 71600914.0, "brut_kar": 71600914.0, "esas_faaliyet_kari": 57093947.0, "favok": 58052792.0, "net_kar": -176660793.0, "brut_marj": 100.0, "favok_marj": 81.1, "net_marj": -246.7, "roe": -36.2, "roic": 3.2, "donen_varliklar": 22968147.0, "duran_varliklar": 774753728.0, "nakit_finansal_yatirim": 1357685.0, "finansal_borclar_kv": 743374.0, "net_borc": 543566.0, "net_borc_favok": 0.02, "ozkaynaklar": 783862673.0}, {"period": "2024/09", "satislar": 111170.0, "brut_kar": 111170.0, "esas_faaliyet_kari": -9625394.0, "favok": -9495731.0, "net_kar": 57646289.0, "brut_marj": 100.0, "favok_marj": -8541.6, "net_marj": 51854.2, "roe": -18.5, "roic": -3.9, "donen_varliklar": 23107815.0, "duran_varliklar": 562680596.0, "nakit_finansal_yatirim": 7257531.0, "finansal_borclar_kv": 0.0, "net_borc": -7257531.0, "net_borc_favok": 0.24, "ozkaynaklar": 581060868.0}, {"period": "2024/06", "satislar": 858543.0, "brut_kar": 858543.0, "esas_faaliyet_kari": -6412938.0, "favok": -6350740.0, "net_kar": -64300859.0, "brut_marj": 100.0, "favok_marj": -739.7, "net_marj": -7489.5, "roe": -32.6, "roic": -3.7, "donen_varliklar": 20704703.0, "duran_varliklar": 562064350.0, "nakit_finansal_yatirim": 5927701.0, "finansal_borclar_kv": 0.0, "net_borc": -5927701.0, "net_borc_favok": 0.21, "ozkaynaklar": 579286725.0}, {"period": "2024/03", "satislar": 0.0, "brut_kar": 0.0, "esas_faaliyet_kari": -7743604.0, "favok": -7743604.0, "net_kar": -107589736.0, "brut_marj": null, "favok_marj": null, "net_marj": null, "roe": -66.8, "roic": -3.6, "donen_varliklar": 33524059.0, "duran_varliklar": 547179583.0, "nakit_finansal_yatirim": 19011129.0, "finansal_borclar_kv": 0.0, "net_borc": -19011129.0, "net_borc_favok": 0.68, "ozkaynaklar": 576942240.0}, {"period": "2023/12", "satislar": 613682.0, "brut_kar": 0.0, "esas_faaliyet_kari": -6391779.0, "favok": -6254017.0, "net_kar": 30003758.0, "brut_marj": 0.0, "favok_marj": -1019.1, "net_marj": 4889.1, "roe": 2.6, "roic": -2.9, "donen_varliklar": 40453486.0, "duran_varliklar": 783239598.0, "nakit_finansal_yatirim": 21946750.0, "finansal_borclar_kv": 0.0, "net_borc": -21946750.0, "net_borc_favok": 0.69, "ozkaynaklar": 821560615.0}]}