{"code": "MEGMT", "updated": "2026-07-02 23:08", "quarters": [{"period": "2026/03", "satislar": 8133438736.0, "brut_kar": 0.0, "esas_faaliyet_kari": 322953347.0, "favok": 492501126.0, "net_kar": 481101194.0, "brut_marj": 0.0, "favok_marj": 6.1, "net_marj": 5.9, "donen_varliklar": 9363624349.0, "duran_varliklar": null, "nakit_finansal_yatirim": 1857666278.0, "finansal_borclar_kv": 5483036780.0, "ozkaynaklar": 4605953109.0}, {"period": "2025/12", "satislar": 8467763950.0, "brut_kar": 0.0, "esas_faaliyet_kari": 263529956.0, "favok": 480609029.0, "net_kar": 459283244.0, "brut_marj": 0.0, "favok_marj": 5.7, "net_marj": 5.4, "donen_varliklar": 9682204412.0, "duran_varliklar": null, "nakit_finansal_yatirim": 1978132938.0, "finansal_borclar_kv": 5422408060.0, "ozkaynaklar": 4368781585.0}, {"period": "2025/09", "satislar": 5985384598.0, "brut_kar": 0.0, "esas_faaliyet_kari": 147869828.0, "favok": 195329448.0, "net_kar": 274332846.0, "brut_marj": 0.0, "favok_marj": 3.3, "net_marj": 4.6, "donen_varliklar": 8146110165.0, "duran_varliklar": null, "nakit_finansal_yatirim": 1874535913.0, "finansal_borclar_kv": 4820756726.0, "ozkaynaklar": 4307283831.0}, {"period": "2025/06", "satislar": 5835354597.0, "brut_kar": 0.0, "esas_faaliyet_kari": 119613549.0, "favok": 299058282.0, "net_kar": 718135773.0, "brut_marj": 0.0, "favok_marj": 5.1, "net_marj": 12.3, "donen_varliklar": 7129454493.0, "duran_varliklar": null, "nakit_finansal_yatirim": 1610279810.0, "finansal_borclar_kv": 4194038711.0, "ozkaynaklar": 3874544381.0}, {"period": "2025/03", "satislar": 5037803724.0, "brut_kar": 0.0, "esas_faaliyet_kari": 202332433.0, "favok": 318877010.0, "net_kar": 165356615.0, "brut_marj": 0.0, "favok_marj": 6.3, "net_marj": 3.3, "donen_varliklar": 6471740476.0, "duran_varliklar": null, "nakit_finansal_yatirim": 1852096514.0, "finansal_borclar_kv": 3812513790.0, "ozkaynaklar": 3805523194.0}, {"period": "2024/12", "satislar": 9681772653.0, "brut_kar": 0.0, "esas_faaliyet_kari": 159147763.0, "favok": 356596091.0, "net_kar": 143255849.0, "brut_marj": 0.0, "favok_marj": 3.7, "net_marj": 1.5, "donen_varliklar": 7157245475.0, "duran_varliklar": null, "nakit_finansal_yatirim": 2155150640.0, "finansal_borclar_kv": 4201869576.0, "ozkaynaklar": 4780415838.0}, {"period": "2024/09", "satislar": 4748914839.0, "brut_kar": 0.0, "esas_faaliyet_kari": 154310216.0, "favok": 247282069.0, "net_kar": 58041464.0, "brut_marj": 0.0, "favok_marj": 5.2, "net_marj": 1.2, "donen_varliklar": 5749457553.0, "duran_varliklar": null, "nakit_finansal_yatirim": 1604210955.0, "finansal_borclar_kv": 3500051289.0, "ozkaynaklar": 3635124071.0}, {"period": "2024/06", "satislar": 4625596376.0, "brut_kar": 0.0, "esas_faaliyet_kari": 253161937.0, "favok": 339961024.0, "net_kar": 213454129.0, "brut_marj": 0.0, "favok_marj": 7.3, "net_marj": 4.6, "donen_varliklar": 5491631513.0, "duran_varliklar": null, "nakit_finansal_yatirim": 1601436924.0, "finansal_borclar_kv": 3191538030.0, "ozkaynaklar": 3450846775.0}, {"period": "2024/03", "satislar": 4420091247.0, "brut_kar": 0.0, "esas_faaliyet_kari": 227974491.0, "favok": 306637915.0, "net_kar": 138406962.0, "brut_marj": 0.0, "favok_marj": 6.9, "net_marj": 3.1, "donen_varliklar": 4737361427.0, "duran_varliklar": null, "nakit_finansal_yatirim": 1477406990.0, "finansal_borclar_kv": 2383608220.0, "ozkaynaklar": 3181749373.0}, {"period": "2023/12", "satislar": 3271351277.0, "brut_kar": 0.0, "esas_faaliyet_kari": 159834145.0, "favok": 229569666.0, "net_kar": 97589266.0, "brut_marj": 0.0, "favok_marj": 7.0, "net_marj": 3.0, "donen_varliklar": 4168103692.0, "duran_varliklar": null, "nakit_finansal_yatirim": 1640761009.0, "finansal_borclar_kv": 1794893189.0, "ozkaynaklar": 2768047202.0}]}