{"code": "PETUN", "updated": "2026-07-02 21:16", "quarters": [{"period": "2026/03", "satislar": 2980840304.0, "brut_kar": 437375985.0, "esas_faaliyet_kari": 0.0, "favok": null, "net_kar": 128453668.0, "brut_marj": 14.7, "favok_marj": null, "net_marj": 4.3, "donen_varliklar": 6610372737.0, "duran_varliklar": 0.0, "nakit_finansal_yatirim": 365004404.0, "finansal_borclar_kv": 2804472669.0, "ozkaynaklar": 10497610768.0}, {"period": "2025/12", "satislar": 11527151551.0, "brut_kar": 2335634259.0, "esas_faaliyet_kari": 0.0, "favok": null, "net_kar": 206725639.0, "brut_marj": 20.3, "favok_marj": null, "net_marj": 1.8, "donen_varliklar": 6360564720.0, "duran_varliklar": 0.0, "nakit_finansal_yatirim": 172300611.0, "finansal_borclar_kv": 2806766663.0, "ozkaynaklar": 10852451555.0}, {"period": "2025/09", "satislar": 7724175565.0, "brut_kar": 1531492208.0, "esas_faaliyet_kari": 0.0, "favok": null, "net_kar": 293672193.0, "brut_marj": 19.8, "favok_marj": null, "net_marj": 3.8, "donen_varliklar": 4989457682.0, "duran_varliklar": 0.0, "nakit_finansal_yatirim": 137140562.0, "finansal_borclar_kv": 1975037170.0, "ozkaynaklar": 8511522294.0}, {"period": "2025/06", "satislar": 4627657459.0, "brut_kar": 1000816388.0, "esas_faaliyet_kari": 0.0, "favok": null, "net_kar": 139757425.0, "brut_marj": 21.6, "favok_marj": null, "net_marj": 3.0, "donen_varliklar": 4465612024.0, "duran_varliklar": 0.0, "nakit_finansal_yatirim": 108846077.0, "finansal_borclar_kv": 1869120554.0, "ozkaynaklar": 7870232974.0}, {"period": "2025/03", "satislar": 2805005804.0, "brut_kar": 676347690.0, "esas_faaliyet_kari": 0.0, "favok": null, "net_kar": 81007685.0, "brut_marj": 24.1, "favok_marj": null, "net_marj": 2.9, "donen_varliklar": 4268064070.0, "duran_varliklar": 0.0, "nakit_finansal_yatirim": 445268033.0, "finansal_borclar_kv": 1530981609.0, "ozkaynaklar": 7394970091.0}, {"period": "2024/12", "satislar": 10585136285.0, "brut_kar": 2029283853.0, "esas_faaliyet_kari": 0.0, "favok": null, "net_kar": 3046646.0, "brut_marj": 19.2, "favok_marj": null, "net_marj": 0.0, "donen_varliklar": 4029566283.0, "duran_varliklar": 0.0, "nakit_finansal_yatirim": 173742472.0, "finansal_borclar_kv": 1967988593.0, "ozkaynaklar": 8775783126.0}, {"period": "2024/09", "satislar": 7678238233.0, "brut_kar": 1369327952.0, "esas_faaliyet_kari": 0.0, "favok": null, "net_kar": 101882169.0, "brut_marj": 17.8, "favok_marj": null, "net_marj": 1.3, "donen_varliklar": 2693493484.0, "duran_varliklar": 0.0, "nakit_finansal_yatirim": 82294317.0, "finansal_borclar_kv": 1190725939.0, "ozkaynaklar": 6185524533.0}, {"period": "2024/06", "satislar": 4583753298.0, "brut_kar": 713988255.0, "esas_faaliyet_kari": 0.0, "favok": null, "net_kar": -103722609.0, "brut_marj": 15.6, "favok_marj": null, "net_marj": -2.3, "donen_varliklar": 2284641781.0, "duran_varliklar": 0.0, "nakit_finansal_yatirim": 130669578.0, "finansal_borclar_kv": 866278274.0, "ozkaynaklar": 5489453066.0}, {"period": "2024/03", "satislar": 2126151830.0, "brut_kar": 354166308.0, "esas_faaliyet_kari": 0.0, "favok": null, "net_kar": 5443481.0, "brut_marj": 16.7, "favok_marj": null, "net_marj": 0.3, "donen_varliklar": 2164473052.0, "duran_varliklar": 0.0, "nakit_finansal_yatirim": 164096437.0, "finansal_borclar_kv": 805726647.0, "ozkaynaklar": 5341412412.0}, {"period": "2023/12", "satislar": 7145609277.0, "brut_kar": 850222831.0, "esas_faaliyet_kari": 0.0, "favok": null, "net_kar": 692112503.0, "brut_marj": 11.9, "favok_marj": null, "net_marj": 9.7, "donen_varliklar": 2260592077.0, "duran_varliklar": 0.0, "nakit_finansal_yatirim": 78624941.0, "finansal_borclar_kv": 738686922.0, "ozkaynaklar": 6741289175.0}]}