{"code": "PINSU", "type": "sinai", "updated": "2026-07-05 11:56", "quarters": [{"period": "2026/03", "satislar": 611598576.0, "brut_kar": 298442220.0, "esas_faaliyet_kari": 10343258.0, "favok": 90209563.0, "net_kar": 10367317.0, "brut_marj": 48.8, "favok_marj": 14.7, "net_marj": 1.7, "roe": 2.7, "roic": 3.3, "donen_varliklar": 714507990.0, "duran_varliklar": 3753620162.0, "nakit_finansal_yatirim": 57859193.0, "finansal_borclar_kv": 539052725.0, "net_borc": 734529069.0, "net_borc_favok": 1.62, "ozkaynaklar": 2705096261.0}, {"period": "2025/12", "satislar": 909989095.0, "brut_kar": 421437580.0, "esas_faaliyet_kari": 16118598.0, "favok": 106165537.0, "net_kar": -19684717.0, "brut_marj": 46.3, "favok_marj": 11.7, "net_marj": -2.2, "roe": 0.2, "roic": 2.6, "donen_varliklar": 719793212.0, "duran_varliklar": 3726075126.0, "nakit_finansal_yatirim": 74874394.0, "finansal_borclar_kv": 591151134.0, "net_borc": 776895724.0, "net_borc_favok": 1.78, "ozkaynaklar": 2698361163.0}, {"period": "2025/09", "satislar": 894248833.0, "brut_kar": 475497122.0, "esas_faaliyet_kari": 98197940.0, "favok": 178852828.0, "net_kar": 65557035.0, "brut_marj": 53.2, "favok_marj": 20.0, "net_marj": 7.3, "roe": -1.2, "roic": 5.4, "donen_varliklar": 631875466.0, "duran_varliklar": 3253556173.0, "nakit_finansal_yatirim": 23689443.0, "finansal_borclar_kv": 388929574.0, "net_borc": 548915548.0, "net_borc_favok": 1.09, "ozkaynaklar": 2369914425.0}, {"period": "2025/06", "satislar": 533111662.0, "brut_kar": 281765986.0, "esas_faaliyet_kari": 31155948.0, "favok": 79088364.0, "net_kar": 7841195.0, "brut_marj": 52.9, "favok_marj": 14.8, "net_marj": 1.5, "roe": 0.6, "roic": 6.7, "donen_varliklar": 633921560.0, "duran_varliklar": 2947272965.0, "nakit_finansal_yatirim": 22465792.0, "finansal_borclar_kv": 389455568.0, "net_borc": 474735350.0, "net_borc_favok": 0.92, "ozkaynaklar": 2142531154.0}, {"period": "2025/03", "satislar": 618564069.0, "brut_kar": 287684510.0, "esas_faaliyet_kari": -22262572.0, "favok": 71758747.0, "net_kar": -48992969.0, "brut_marj": 46.5, "favok_marj": 11.6, "net_marj": -7.9, "roe": 2.6, "roic": 5.8, "donen_varliklar": 615010317.0, "duran_varliklar": 2909938255.0, "nakit_finansal_yatirim": 25914467.0, "finansal_borclar_kv": 452337773.0, "net_borc": 626038949.0, "net_borc_favok": 1.23, "ozkaynaklar": 2028032497.0}, {"period": "2024/12", "satislar": 667241660.0, "brut_kar": 388438752.0, "esas_faaliyet_kari": 104117473.0, "favok": 172444244.0, "net_kar": -48405361.0, "brut_marj": 58.2, "favok_marj": 25.8, "net_marj": -7.3, "roe": 2.2, "roic": 3.6, "donen_varliklar": 622673748.0, "duran_varliklar": 3281376350.0, "nakit_finansal_yatirim": 56218064.0, "finansal_borclar_kv": 449226347.0, "net_borc": 458418533.0, "net_borc_favok": 1.13, "ozkaynaklar": 2462628832.0}, {"period": "2024/09", "satislar": 908810206.0, "brut_kar": 451886770.0, "esas_faaliyet_kari": 123087004.0, "favok": 191743883.0, "net_kar": 100822326.0, "brut_marj": 49.7, "favok_marj": 21.1, "net_marj": 11.1, "roe": 30.5, "roic": 2.2, "donen_varliklar": 524407405.0, "duran_varliklar": 2100446229.0, "nakit_finansal_yatirim": 15738376.0, "finansal_borclar_kv": 290041825.0, "net_borc": 327888304.0, "net_borc_favok": 1.06, "ozkaynaklar": 1582461038.0}, {"period": "2024/06", "satislar": 581229518.0, "brut_kar": 278254040.0, "esas_faaliyet_kari": 2225164.0, "favok": 74762707.0, "net_kar": 38681498.0, "brut_marj": 47.9, "favok_marj": 12.9, "net_marj": 6.7, "roe": 32.3, "roic": -0.7, "donen_varliklar": 507264226.0, "duran_varliklar": 1938519487.0, "nakit_finansal_yatirim": 56628755.0, "finansal_borclar_kv": 338942794.0, "net_borc": 340154122.0, "net_borc_favok": 1.55, "ozkaynaklar": 1384491900.0}, {"period": "2024/03", "satislar": 404157607.0, "brut_kar": 132791450.0, "esas_faaliyet_kari": -86331545.0, "favok": -32931524.0, "net_kar": -46038948.0, "brut_marj": 32.9, "favok_marj": -8.1, "net_marj": -11.4, "roe": 27.2, "roic": 4.3, "donen_varliklar": 411386580.0, "duran_varliklar": 1763548975.0, "nakit_finansal_yatirim": 37656943.0, "finansal_borclar_kv": 296746214.0, "net_borc": 297147819.0, "net_borc_favok": 0.99, "ozkaynaklar": 1250802893.0}, {"period": "2023/12", "satislar": 436776612.0, "brut_kar": 223346665.0, "esas_faaliyet_kari": 16481049.0, "favok": 76329401.0, "net_kar": 203127656.0, "brut_marj": 51.1, "favok_marj": 17.5, "net_marj": 46.5, "roe": 22.9, "roic": 2.7, "donen_varliklar": 469056540.0, "duran_varliklar": 2227816364.0, "nakit_finansal_yatirim": 35583769.0, "finansal_borclar_kv": 353331747.0, "net_borc": 364129621.0, "net_borc_favok": 1.36, "ozkaynaklar": 1618522478.0}]}