{"code": "RODRG", "updated": "2026-07-02 21:18", "quarters": [{"period": "2026/03", "satislar": 17630402.0, "brut_kar": 10841330.0, "esas_faaliyet_kari": 0.0, "favok": null, "net_kar": -51595.0, "brut_marj": 61.5, "favok_marj": null, "net_marj": -0.3, "donen_varliklar": 103560056.0, "duran_varliklar": 0.0, "nakit_finansal_yatirim": 8590632.0, "finansal_borclar_kv": 2067332.0, "ozkaynaklar": 76967995.0}, {"period": "2025/12", "satislar": 97501515.0, "brut_kar": 56644421.0, "esas_faaliyet_kari": 0.0, "favok": null, "net_kar": 4547023.0, "brut_marj": 58.1, "favok_marj": null, "net_marj": 4.7, "donen_varliklar": 93231324.0, "duran_varliklar": 0.0, "nakit_finansal_yatirim": 8183230.0, "finansal_borclar_kv": 1572801.0, "ozkaynaklar": 76587663.0}, {"period": "2025/09", "satislar": 62482046.0, "brut_kar": 28447872.0, "esas_faaliyet_kari": 0.0, "favok": null, "net_kar": 3653094.0, "brut_marj": 45.5, "favok_marj": null, "net_marj": 5.8, "donen_varliklar": 95391133.0, "duran_varliklar": 0.0, "nakit_finansal_yatirim": 8603252.0, "finansal_borclar_kv": 5432513.0, "ozkaynaklar": 74466457.0}, {"period": "2025/06", "satislar": 39555953.0, "brut_kar": 24140769.0, "esas_faaliyet_kari": 0.0, "favok": null, "net_kar": -13811900.0, "brut_marj": 61.0, "favok_marj": null, "net_marj": -34.9, "donen_varliklar": 72044743.0, "duran_varliklar": 0.0, "nakit_finansal_yatirim": 101294.0, "finansal_borclar_kv": 5488983.0, "ozkaynaklar": 54878504.0}, {"period": "2025/03", "satislar": 28479296.0, "brut_kar": 17708098.0, "esas_faaliyet_kari": 0.0, "favok": null, "net_kar": -9165195.0, "brut_marj": 62.2, "favok_marj": null, "net_marj": -32.2, "donen_varliklar": 75915865.0, "duran_varliklar": 0.0, "nakit_finansal_yatirim": 9326975.0, "finansal_borclar_kv": 1469408.0, "ozkaynaklar": 61217371.0}, {"period": "2024/12", "satislar": 125982890.0, "brut_kar": 87571215.0, "esas_faaliyet_kari": 0.0, "favok": null, "net_kar": -192719.0, "brut_marj": 69.5, "favok_marj": null, "net_marj": -0.2, "donen_varliklar": 111607750.0, "duran_varliklar": 0.0, "nakit_finansal_yatirim": 6405498.0, "finansal_borclar_kv": 2031473.0, "ozkaynaklar": 86970982.0}, {"period": "2024/09", "satislar": 83245362.0, "brut_kar": 45268821.0, "esas_faaliyet_kari": 0.0, "favok": null, "net_kar": -13275284.0, "brut_marj": 54.4, "favok_marj": null, "net_marj": -15.9, "donen_varliklar": 79465850.0, "duran_varliklar": 0.0, "nakit_finansal_yatirim": 5772706.0, "finansal_borclar_kv": 1548251.0, "ozkaynaklar": 56102918.0}, {"period": "2024/06", "satislar": 53332230.0, "brut_kar": 31071074.0, "esas_faaliyet_kari": 0.0, "favok": null, "net_kar": -12453096.0, "brut_marj": 58.3, "favok_marj": null, "net_marj": -23.4, "donen_varliklar": 78993905.0, "duran_varliklar": 0.0, "nakit_finansal_yatirim": 5932771.0, "finansal_borclar_kv": 1528179.0, "ozkaynaklar": 66055565.0}, {"period": "2024/03", "satislar": 21955826.0, "brut_kar": 7876766.0, "esas_faaliyet_kari": 0.0, "favok": null, "net_kar": 8715431.0, "brut_marj": 35.9, "favok_marj": null, "net_marj": 39.7, "donen_varliklar": 72107529.0, "duran_varliklar": 0.0, "nakit_finansal_yatirim": 5874668.0, "finansal_borclar_kv": 2010319.0, "ozkaynaklar": 71691527.0}, {"period": "2023/12", "satislar": 57328458.0, "brut_kar": 24753516.0, "esas_faaliyet_kari": 0.0, "favok": null, "net_kar": 15549367.0, "brut_marj": 43.2, "favok_marj": null, "net_marj": 27.1, "donen_varliklar": 68878694.0, "duran_varliklar": 0.0, "nakit_finansal_yatirim": 7051388.0, "finansal_borclar_kv": 3745692.0, "ozkaynaklar": 46542844.0}]}