{"code": "RUZYE", "type": "sinai", "updated": "2026-07-04 10:56", "quarters": [{"period": "2026/03", "satislar": 66578416.0, "brut_kar": -26324748.0, "esas_faaliyet_kari": -46217359.0, "favok": -18399000.0, "net_kar": -81499033.0, "brut_marj": -39.5, "favok_marj": -27.6, "net_marj": -122.4, "roe": -2.4, "roic": -2.7, "donen_varliklar": 543430411.0, "duran_varliklar": 1225916862.0, "nakit_finansal_yatirim": 461632008.0, "finansal_borclar_kv": 10349697.0, "net_borc": -426489278.0, "net_borc_favok": -10.6, "ozkaynaklar": 1571604579.0}, {"period": "2025/12", "satislar": 99976026.0, "brut_kar": -5567418.0, "esas_faaliyet_kari": -32583047.0, "favok": 3809433.0, "net_kar": -39709232.0, "brut_marj": -5.6, "favok_marj": 3.8, "net_marj": -39.7, "roe": -0.3, "roic": -2.6, "donen_varliklar": 540316544.0, "duran_varliklar": 1269419935.0, "nakit_finansal_yatirim": 445738519.0, "finansal_borclar_kv": 98373.0, "net_borc": -445640146.0, "net_borc_favok": -12.28, "ozkaynaklar": 1652819796.0}, {"period": "2025/09", "satislar": 92226780.0, "brut_kar": 22432534.0, "esas_faaliyet_kari": 4348696.0, "favok": 23014804.0, "net_kar": 15397294.0, "brut_marj": 24.3, "favok_marj": 25.0, "net_marj": 16.7, "roe": 10.7, "roic": -3.1, "donen_varliklar": 779672531.0, "duran_varliklar": 846012977.0, "nakit_finansal_yatirim": 692836779.0, "finansal_borclar_kv": 28072994.0, "net_borc": -664763785.0, "net_borc_favok": -43.37, "ozkaynaklar": 1473174710.0}, {"period": "2025/06", "satislar": 78686296.0, "brut_kar": 27283316.0, "esas_faaliyet_kari": 16459599.0, "favok": 31824726.0, "net_kar": 71519339.0, "brut_marj": 34.7, "favok_marj": 40.4, "net_marj": 90.9, "roe": 7.6, "roic": -5.6, "donen_varliklar": 685424030.0, "duran_varliklar": 783997472.0, "nakit_finansal_yatirim": 577594152.0, "finansal_borclar_kv": 0.0, "net_borc": -577594152.0, "net_borc_favok": 21.89, "ozkaynaklar": 1357306052.0}, {"period": "2025/03", "satislar": 35089572.0, "brut_kar": -25319943.0, "esas_faaliyet_kari": -46479649.0, "favok": -22361365.0, "net_kar": -52560027.0, "brut_marj": -72.2, "favok_marj": -63.7, "net_marj": -149.8, "roe": 0.1, "roic": -8.2, "donen_varliklar": 556833039.0, "duran_varliklar": 781104271.0, "nakit_finansal_yatirim": 518710301.0, "finansal_borclar_kv": 0.0, "net_borc": -518710301.0, "net_borc_favok": 8.58, "ozkaynaklar": 1229598060.0}, {"period": "2024/12", "satislar": 66174403.0, "brut_kar": -18095265.0, "esas_faaliyet_kari": -35685265.0, "favok": -17148892.0, "net_kar": 97360240.0, "brut_marj": -27.3, "favok_marj": -25.9, "net_marj": 147.1, "roe": 1.5, "roic": -4.2, "donen_varliklar": 669882954.0, "duran_varliklar": 943812170.0, "nakit_finansal_yatirim": 654004111.0, "finansal_borclar_kv": 0.0, "net_borc": -654004111.0, "net_borc_favok": 28.84, "ozkaynaklar": 1510567563.0}, {"period": "2024/09", "satislar": 44036264.0, "brut_kar": -10966957.0, "esas_faaliyet_kari": -35705551.0, "favok": -18702051.0, "net_kar": -29294422.0, "brut_marj": -24.9, "favok_marj": -42.5, "net_marj": -66.5, "roe": -5.9, "roic": -0.9, "donen_varliklar": 468178575.0, "duran_varliklar": 618053335.0, "nakit_finansal_yatirim": 427266268.0, "finansal_borclar_kv": 0.0, "net_borc": -427266268.0, "net_borc_favok": -9.49, "ozkaynaklar": 995792846.0}, {"period": "2024/06", "satislar": 28158074.0, "brut_kar": -1004840.0, "esas_faaliyet_kari": -16607492.0, "favok": -2263420.0, "net_kar": -14928352.0, "brut_marj": -3.6, "favok_marj": -8.0, "net_marj": -53.0, "roe": -13.2, "roic": 2.1, "donen_varliklar": 458356508.0, "duran_varliklar": 521000147.0, "nakit_finansal_yatirim": 407765232.0, "finansal_borclar_kv": 0.0, "net_borc": -407765232.0, "net_borc_favok": -5.17, "ozkaynaklar": 933103501.0}, {"period": "2024/03", "satislar": 65788636.0, "brut_kar": 14828775.0, "esas_faaliyet_kari": 2791846.0, "favok": 15436704.0, "net_kar": -33696722.0, "brut_marj": 22.5, "favok_marj": 23.5, "net_marj": -51.2, "roe": -5.9, "roic": 4.8, "donen_varliklar": 446936391.0, "duran_varliklar": 531813371.0, "nakit_finansal_yatirim": 390980317.0, "finansal_borclar_kv": 92159.0, "net_borc": -390888158.0, "net_borc_favok": -3.68, "ozkaynaklar": 894342564.0}, {"period": "2023/12", "satislar": 83356181.0, "brut_kar": 50445875.0, "esas_faaliyet_kari": 37533499.0, "favok": 50560776.0, "net_kar": 31357288.0, "brut_marj": 60.5, "favok_marj": 60.7, "net_marj": 37.6, "roe": -5.8, "roic": 3.4, "donen_varliklar": 538997987.0, "duran_varliklar": 575183293.0, "nakit_finansal_yatirim": 511804135.0, "finansal_borclar_kv": 133058.0, "net_borc": -511671077.0, "net_borc_favok": -5.41, "ozkaynaklar": 1067870068.0}]}