{"code": "TRENJ", "type": "sinai", "updated": "2026-07-04 11:02", "quarters": [{"period": "2026/03", "satislar": 8978052000.0, "brut_kar": 4919297000.0, "esas_faaliyet_kari": 3918138000.0, "favok": 4205293000.0, "net_kar": 1314132000.0, "brut_marj": 54.8, "favok_marj": 46.8, "net_marj": 14.6, "roe": 11.3, "roic": 10.8, "donen_varliklar": 27831034000.0, "duran_varliklar": 34217941000.0, "nakit_finansal_yatirim": 23240965000.0, "finansal_borclar_kv": 115211000.0, "net_borc": -23125380000.0, "net_borc_favok": -2.64, "ozkaynaklar": 51246335000.0}, {"period": "2025/12", "satislar": 5483777576.0, "brut_kar": 2377709073.0, "esas_faaliyet_kari": 1158224802.0, "favok": 1616578949.0, "net_kar": -687971427.0, "brut_marj": 43.4, "favok_marj": 29.5, "net_marj": -12.5, "roe": 8.6, "roic": 6.3, "donen_varliklar": 23244490133.0, "duran_varliklar": 32737307736.0, "nakit_finansal_yatirim": 19477826172.0, "finansal_borclar_kv": 112315799.0, "net_borc": -19364073248.0, "net_borc_favok": -3.54, "ozkaynaklar": 49933603971.0}, {"period": "2025/09", "satislar": 6244377000.0, "brut_kar": 2861690000.0, "esas_faaliyet_kari": 1871834000.0, "favok": 2258004000.0, "net_kar": 3026330000.0, "brut_marj": 45.8, "favok_marj": 36.2, "net_marj": 48.5, "roe": 12.4, "roic": 4.6, "donen_varliklar": 21289024000.0, "duran_varliklar": 28441233000.0, "nakit_finansal_yatirim": 17882529000.0, "finansal_borclar_kv": 65000000.0, "net_borc": -17817529000.0, "net_borc_favok": -4.54, "ozkaynaklar": 44709614000.0}, {"period": "2025/06", "satislar": 2016672000.0, "brut_kar": 1125559000.0, "esas_faaliyet_kari": 479476000.0, "favok": 663478000.0, "net_kar": 1259950000.0, "brut_marj": 55.8, "favok_marj": 32.9, "net_marj": 62.5, "roe": 3.8, "roic": 2.4, "donen_varliklar": 18004007000.0, "duran_varliklar": 24881780000.0, "nakit_finansal_yatirim": 14282876000.0, "finansal_borclar_kv": 20965000.0, "net_borc": -14260957000.0, "net_borc_favok": -6.25, "ozkaynaklar": 38885442000.0}, {"period": "2025/03", "satislar": 5762596000.0, "brut_kar": 1661067000.0, "esas_faaliyet_kari": 671448000.0, "favok": 925396000.0, "net_kar": 355493000.0, "brut_marj": 28.8, "favok_marj": 16.1, "net_marj": 6.2, "roe": -0.1, "roic": 2.1, "donen_varliklar": 16831993000.0, "duran_varliklar": 22557492000.0, "nakit_finansal_yatirim": 13230800000.0, "finansal_borclar_kv": 20600000.0, "net_borc": -13208797000.0, "net_borc_favok": -5.3, "ozkaynaklar": 35402466000.0}, {"period": "2024/12", "satislar": 1555353275.0, "brut_kar": 449289711.0, "esas_faaliyet_kari": -277843414.0, "favok": 76478346.0, "net_kar": 90034763.0, "brut_marj": 28.9, "favok_marj": 4.9, "net_marj": 5.8, "roe": -2.6, "roic": 1.4, "donen_varliklar": 18495139723.0, "duran_varliklar": 27617497328.0, "nakit_finansal_yatirim": 13668512586.0, "finansal_borclar_kv": 27507023.0, "net_borc": -13638635103.0, "net_borc_favok": -5.35, "ozkaynaklar": 41826219572.0}, {"period": "2024/09", "satislar": 3238981000.0, "brut_kar": 1189650000.0, "esas_faaliyet_kari": 378723000.0, "favok": 617313000.0, "net_kar": -436534000.0, "brut_marj": 36.7, "favok_marj": 19.1, "net_marj": -13.5, "roe": 8.9, "roic": 5.5, "donen_varliklar": 15407567000.0, "duran_varliklar": 19577339000.0, "nakit_finansal_yatirim": 12698718000.0, "finansal_borclar_kv": 505000.0, "net_borc": -12696485000.0, "net_borc_favok": -2.97, "ozkaynaklar": 31898029000.0}, {"period": "2024/06", "satislar": 3154382000.0, "brut_kar": 941763000.0, "esas_faaliyet_kari": 210282000.0, "favok": 871034000.0, "net_kar": -35703000.0, "brut_marj": 29.9, "favok_marj": 27.6, "net_marj": -1.1, "roe": -0.4, "roic": 8.6, "donen_varliklar": 13983554000.0, "duran_varliklar": 17969752000.0, "nakit_finansal_yatirim": 9867455000.0, "finansal_borclar_kv": 645000.0, "net_borc": -9865082000.0, "net_borc_favok": -1.88, "ozkaynaklar": 28723905000.0}, {"period": "2024/03", "satislar": 4162031000.0, "brut_kar": 1227141000.0, "esas_faaliyet_kari": 449243000.0, "favok": 986524000.0, "net_kar": -624276000.0, "brut_marj": 29.5, "favok_marj": 23.7, "net_marj": -15.0, "roe": 3.8, "roic": 8.8, "donen_varliklar": 12840532000.0, "duran_varliklar": 17452089000.0, "nakit_finansal_yatirim": 10804718000.0, "finansal_borclar_kv": 469000.0, "net_borc": -10803659000.0, "net_borc_favok": -2.33, "ozkaynaklar": 26679404000.0}, {"period": "2023/12", "satislar": 2583646000.0, "brut_kar": 1884485000.0, "esas_faaliyet_kari": 1315845000.0, "favok": 1798568000.0, "net_kar": 3192781000.0, "brut_marj": 72.9, "favok_marj": 69.6, "net_marj": 123.6, "roe": 2.7, "roic": 4.9, "donen_varliklar": 17453969000.0, "duran_varliklar": 21655001000.0, "nakit_finansal_yatirim": 14360403000.0, "finansal_borclar_kv": 557800000.0, "net_borc": -13799562000.0, "net_borc_favok": -3.86, "ozkaynaklar": 35134358000.0}]}