{"code": "VAKKO", "updated": "2026-07-02 21:25", "quarters": [{"period": "2026/03", "satislar": 4724223938.0, "brut_kar": 2452424722.0, "esas_faaliyet_kari": 0.0, "favok": null, "net_kar": -91204856.0, "brut_marj": 51.9, "favok_marj": null, "net_marj": -1.9, "donen_varliklar": 9899905602.0, "duran_varliklar": 0.0, "nakit_finansal_yatirim": 1492983916.0, "finansal_borclar_kv": 1429103155.0, "ozkaynaklar": 10649628587.0}, {"period": "2025/12", "satislar": 21845806553.0, "brut_kar": 10057773564.0, "esas_faaliyet_kari": 0.0, "favok": null, "net_kar": 62707162.0, "brut_marj": 46.0, "favok_marj": null, "net_marj": 0.3, "donen_varliklar": 10359257536.0, "duran_varliklar": 0.0, "nakit_finansal_yatirim": 2104345757.0, "finansal_borclar_kv": 843926705.0, "ozkaynaklar": 10746826264.0}, {"period": "2025/09", "satislar": 13011935665.0, "brut_kar": 6277285639.0, "esas_faaliyet_kari": 0.0, "favok": null, "net_kar": -15998007.0, "brut_marj": 48.2, "favok_marj": null, "net_marj": -0.1, "donen_varliklar": 8638981639.0, "duran_varliklar": 0.0, "nakit_finansal_yatirim": 400080668.0, "finansal_borclar_kv": 997024219.0, "ozkaynaklar": 9190076294.0}, {"period": "2025/06", "satislar": 8065185291.0, "brut_kar": 3713399456.0, "esas_faaliyet_kari": 0.0, "favok": null, "net_kar": -15087236.0, "brut_marj": 46.0, "favok_marj": null, "net_marj": -0.2, "donen_varliklar": 7956054463.0, "duran_varliklar": 0.0, "nakit_finansal_yatirim": 832497837.0, "finansal_borclar_kv": 996533375.0, "ozkaynaklar": 8552816831.0}, {"period": "2025/03", "satislar": 4566465080.0, "brut_kar": 2310333375.0, "esas_faaliyet_kari": 0.0, "favok": null, "net_kar": 16451680.0, "brut_marj": 50.6, "favok_marj": null, "net_marj": 0.4, "donen_varliklar": 8528024080.0, "duran_varliklar": 0.0, "nakit_finansal_yatirim": 1130112776.0, "finansal_borclar_kv": 912161225.0, "ozkaynaklar": 8725115225.0}, {"period": "2024/12", "satislar": 19444634113.0, "brut_kar": 9911124175.0, "esas_faaliyet_kari": 0.0, "favok": null, "net_kar": 1055629623.0, "brut_marj": 51.0, "favok_marj": null, "net_marj": 5.4, "donen_varliklar": 10565732424.0, "duran_varliklar": 0.0, "nakit_finansal_yatirim": 2187062633.0, "finansal_borclar_kv": 1145514185.0, "ozkaynaklar": 10366075903.0}, {"period": "2024/09", "satislar": 12929832168.0, "brut_kar": 6828465284.0, "esas_faaliyet_kari": 0.0, "favok": null, "net_kar": 541108090.0, "brut_marj": 52.8, "favok_marj": null, "net_marj": 4.2, "donen_varliklar": 7230049807.0, "duran_varliklar": 0.0, "nakit_finansal_yatirim": 663071706.0, "finansal_borclar_kv": 968947412.0, "ozkaynaklar": 7171037246.0}, {"period": "2024/06", "satislar": 8201021417.0, "brut_kar": 4419975215.0, "esas_faaliyet_kari": 0.0, "favok": null, "net_kar": 490347417.0, "brut_marj": 53.9, "favok_marj": null, "net_marj": 6.0, "donen_varliklar": 6678171649.0, "duran_varliklar": 0.0, "nakit_finansal_yatirim": 862202958.0, "finansal_borclar_kv": 842191460.0, "ozkaynaklar": 6580671375.0}, {"period": "2024/03", "satislar": 3673155949.0, "brut_kar": 1914789245.0, "esas_faaliyet_kari": 0.0, "favok": null, "net_kar": 409775270.0, "brut_marj": 52.1, "favok_marj": null, "net_marj": 11.2, "donen_varliklar": 6355337700.0, "duran_varliklar": 0.0, "nakit_finansal_yatirim": 953807420.0, "finansal_borclar_kv": 695002175.0, "ozkaynaklar": 6405910647.0}, {"period": "2023/12", "satislar": 14239328628.0, "brut_kar": 8094588689.0, "esas_faaliyet_kari": 0.0, "favok": null, "net_kar": 2807238574.0, "brut_marj": 56.8, "favok_marj": null, "net_marj": 19.7, "donen_varliklar": 7852859932.0, "duran_varliklar": 0.0, "nakit_finansal_yatirim": 1391390353.0, "finansal_borclar_kv": 892923543.0, "ozkaynaklar": 7545029489.0}]}